whois21/API.py
whois21/ASN.py
whois21/DNS.py
whois21/IP.py
whois21/__init__.py
whois21/__main__.py
whois21/vcard-map.json
whois21-1.4.7.dist-info/licenses/LICENSE
whois21-1.4.7.dist-info/METADATA
whois21-1.4.7.dist-info/WHEEL
whois21-1.4.7.dist-info/entry_points.txt
whois21-1.4.7.dist-info/top_level.txt
whois21-1.4.7.dist-info/RECORD
