Metadata-Version: 2.4
Name: whois21
Version: 1.4.7
Summary: A simple and easy to use Python package that lets you query whois/RDAP information of a domain/IP.
Author-email: "CodeWriter21(Mehrad Pooryoussof)" <CodeWriter21@gmail.com>
License: Apache License 2.0
Project-URL: Homepage, https://github.com/MPCodeWriter21/whois21
Project-URL: Donations, https://github.com/MPCodeWriter21/whois21/blob/master/DONATE.md
Project-URL: Source, https://github.com/MPCodeWriter21/whois21
Keywords: python,python3,CodeWriter21,WHOIS,whois21,RDAP,Registration Data Access Protocol,DNS,ASN
Classifier: Programming Language :: Python :: 3
Requires-Python: >=3.9
License-File: LICENSE
Requires-Dist: log21>=3.0.0
Requires-Dist: chardet>=5.2.0
Requires-Dist: requests>=2.31.0
Requires-Dist: importlib_resources>=6.1.0
Provides-Extra: dev
Requires-Dist: yapf>=0.40.1; extra == "dev"
Requires-Dist: isort>=5.12.0; extra == "dev"
Requires-Dist: pylint>=2.17.4; extra == "dev"
Requires-Dist: docformatter>=1.7.5; extra == "dev"
Dynamic: license-file
